camera_master/__init__.py
camera_master/access_control.py
camera_master/age_gender.py
camera_master/attendance.py
camera_master/attention.py
camera_master/camera_manager.py
camera_master/cli.py
camera_master/emotion.py
camera_master/fatigue.py
camera_master/gamification.py
camera_master/gesture.py
camera_master/mask_detection.py
camera_master/mood_tracker.py
camera_master/reports.py
camera_master/spoof.py
camera_master/utils.py
camera_master/visualization.py
camera_master-0.2.0.dist-info/licenses/LICENSE
camera_master-0.2.0.dist-info/METADATA
camera_master-0.2.0.dist-info/WHEEL
camera_master-0.2.0.dist-info/entry_points.txt
camera_master-0.2.0.dist-info/top_level.txt
camera_master-0.2.0.dist-info/RECORD
