Metadata-Version: 2.4
Name: camera-master
Version: 0.2.0
Summary: AI-powered education monitoring system with face recognition, gesture detection, and emotion analysis
Home-page: https://github.com/RNSsanjay/camera-master
Author: RNS Sanjay
Author-email: RNS <contact@example.com>
License: MIT
Project-URL: Homepage, https://github.com/RNSsanjay/camera-master
Project-URL: Documentation, https://github.com/RNSsanjay/camera-master#readme
Project-URL: Repository, https://github.com/RNSsanjay/camera-master
Keywords: face-recognition,gesture-detection,emotion-analysis,education,ai,computer-vision
Classifier: Development Status :: 4 - Beta
Classifier: Intended Audience :: Education
Classifier: Topic :: Education
Classifier: Topic :: Scientific/Engineering :: Artificial Intelligence
Classifier: License :: OSI Approved :: MIT License
Classifier: Programming Language :: Python :: 3
Classifier: Programming Language :: Python :: 3.8
Classifier: Programming Language :: Python :: 3.9
Classifier: Programming Language :: Python :: 3.10
Classifier: Programming Language :: Python :: 3.11
Requires-Python: >=3.8
License-File: LICENSE
Requires-Dist: opencv-python>=4.8.0
Requires-Dist: mediapipe>=0.10.0
Requires-Dist: deepface>=0.0.79
Requires-Dist: numpy>=1.24.0
Requires-Dist: pandas>=2.0.0
Requires-Dist: matplotlib>=3.7.0
Requires-Dist: pyttsx3>=2.90
Requires-Dist: streamlit>=1.28.0
Requires-Dist: gradio>=3.50.0
Requires-Dist: tf-keras>=2.15.0
Requires-Dist: pillow>=10.0.0
Requires-Dist: scipy>=1.11.0
Provides-Extra: dev
Requires-Dist: pytest>=7.4.0; extra == "dev"
Requires-Dist: pytest-cov>=4.1.0; extra == "dev"
Requires-Dist: black>=23.7.0; extra == "dev"
Requires-Dist: flake8>=6.1.0; extra == "dev"
Requires-Dist: mypy>=1.5.0; extra == "dev"
Dynamic: author
Dynamic: home-page
Dynamic: license-file
Dynamic: requires-python
